LICENSE
MANIFEST.in
README.md
package.json
pyproject.toml
setup.py
tsconfig.json
glab/__init__.py
glab/_version.py
glab/handlers.py
glab.egg-info/PKG-INFO
glab.egg-info/SOURCES.txt
glab.egg-info/dependency_links.txt
glab.egg-info/not-zip-safe
glab.egg-info/requires.txt
glab.egg-info/top_level.txt
glab/labextension/gcollective-glab-0.1.0.tgz
jupyter-config/glab.json
src/glab.ts
src/index.ts
src/svg.d.ts
src/.ipynb_checkpoints/glab-checkpoint.ts
src/.ipynb_checkpoints/index-checkpoint.ts
style/Python-logo-notext.svg
style/index.css
style/.ipynb_checkpoints/index-checkpoint.css